[
  {
    "id_lms_module": 702,
    "module_name": "CCVO - Video 1",
    "module_desc": null,
    "params": "{\"total_elements\":1,\"elements\":[6101]}",
    "state": 1,
    "date_add": null,
    "date_mod": null,
    "date_removed": null,
    "id_add": null,
    "id_mod": null,
    "id_removed": null
  },
  {
    "id_lms_module": 703,
    "module_name": "CCVO - Quiz 1",
    "module_desc": null,
    "params": "{\"total_elements\":1,\"elements\":[6110]}",
    "state": 1,
    "date_add": null,
    "date_mod": null,
    "date_removed": null,
    "id_add": null,
    "id_mod": null,
    "id_removed": null
  },
  {
    "id_lms_module": 704,
    "module_name": "CCVO - Video 2",
    "module_desc": null,
    "params": "{\"total_elements\":1,\"elements\":[6102]}",
    "state": 1,
    "date_add": null,
    "date_mod": null,
    "date_removed": null,
    "id_add": null,
    "id_mod": null,
    "id_removed": null
  },
  {
    "id_lms_module": 705,
    "module_name": "CCVO - Quiz 2",
    "module_desc": null,
    "params": "{\"total_elements\":1,\"elements\":[6103]}",
    "state": 1,
    "date_add": null,
    "date_mod": null,
    "date_removed": null,
    "id_add": null,
    "id_mod": null,
    "id_removed": null
  },
  {
    "id_lms_module": 706,
    "module_name": "CCVO - Response Card",
    "module_desc": null,
    "params": "{\"total_elements\":1,\"elements\":[6104]}",
    "state": 1,
    "date_add": null,
    "date_mod": null,
    "date_removed": null,
    "id_add": null,
    "id_mod": null,
    "id_removed": null
  },
  {
    "id_lms_module": 707,
    "module_name": "FAM Foundations",
    "module_desc": null,
    "params": "{\"total_elements\":11,\"elements\":[6105,6106,6114,6107,6108,6109,6115,6111,6112,6113,6116]}",
    "state": 1,
    "date_add": null,
    "date_mod": null,
    "date_removed": null,
    "id_add": null,
    "id_mod": null,
    "id_removed": null
  },
  {
    "id_lms_module": 708,
    "module_name": "Advocate Clinic - FAM Overview",
    "module_desc": null,
    "params": "{\"total_elements\":1,\"elements\":[6117]}",
    "state": 1,
    "date_add": null,
    "date_mod": null,
    "date_removed": null,
    "id_add": null,
    "id_mod": null,
    "id_removed": null
  },
  {
    "id_lms_module": 709,
    "module_name": "Advocate Clinic - ReMoved",
    "module_desc": null,
    "params": "{\"total_elements\":1,\"elements\":[6118]}",
    "state": 1,
    "date_add": null,
    "date_mod": null,
    "date_removed": null,
    "id_add": null,
    "id_mod": null,
    "id_removed": null
  },
  {
    "id_lms_module": 710,
    "module_name": "Advocate Clinic - What is a Care Community",
    "module_desc": null,
    "params": "{\"total_elements\":1,\"elements\":[6123]}",
    "state": 1,
    "date_add": null,
    "date_mod": null,
    "date_removed": null,
    "id_add": null,
    "id_mod": null,
    "id_removed": null
  },
  {
    "id_lms_module": 711,
    "module_name": "Advocate Clinic - Roles in a Care Community",
    "module_desc": null,
    "params": "{\"total_elements\":1,\"elements\":[6121]}",
    "state": 1,
    "date_add": null,
    "date_mod": null,
    "date_removed": null,
    "id_add": null,
    "id_mod": null,
    "id_removed": null
  },
  {
    "id_lms_module": 712,
    "module_name": "Advocate Clinic - Prayer Guide",
    "module_desc": null,
    "params": "{\"total_elements\":1,\"elements\":[6122]}",
    "state": 1,
    "date_add": null,
    "date_mod": null,
    "date_removed": null,
    "id_add": null,
    "id_mod": null,
    "id_removed": null
  },
  {
    "id_lms_module": 713,
    "module_name": "Advocate Clinic - Promise Serves Overview",
    "module_desc": null,
    "params": "{\"total_elements\":1,\"elements\":[6119]}",
    "state": 1,
    "date_add": null,
    "date_mod": null,
    "date_removed": null,
    "id_add": null,
    "id_mod": null,
    "id_removed": null
  },
  {
    "id_lms_module": 714,
    "module_name": "Advocate Clinic - Resources Overview",
    "module_desc": null,
    "params": "{\"total_elements\":1,\"elements\":[6120]}",
    "state": 1,
    "date_add": null,
    "date_mod": null,
    "date_removed": null,
    "id_add": null,
    "id_mod": null,
    "id_removed": null
  }
]